This XML file does not appear to have any style information associated with it. The document tree is shown below.
        <!--
         Published by JAX-WS RI (http://jax-ws.java.net). RI's version is JAX-WS RI 2.2.9-b130926.1035 svn-revision#5f6196f2b90e9460065a4c2f4e30e065b245e51e.
        -->
        <!--
         Generated by JAX-WS RI (http://jax-ws.java.net). RI's version is JAX-WS RI 2.2.9-b130926.1035 svn-revision#5f6196f2b90e9460065a4c2f4e30e065b245e51e.
        -->
<definitions xmlns:wsam="http://www.w3.org/2007/05/addressing/metadata"
             xmlns:soap="http://schemas.xmlsoap.org/wsdl/soap/" xmlns:tns="http://ServiceWsdl/"
             xmlns:xsd="http://www.w3.org/2001/XMLSchema" xmlns="http://schemas.xmlsoap.org/wsdl/"
             targetNamespace="http://ServiceWsdl/" name="ServiceWsdlImplService">
    <types/>
    <message name="getWsdl"/>
    <message name="getWsdlResponse">
        <part name="return" type="xsd:string"/>
    </message>
    <portType name="ServiceWsdl">
        <operation name="getWsdl">
            <input wsam:Action="http://ServiceWsdl/ServiceWsdl/getWsdlRequest" message="tns:getWsdl"/>
            <output wsam:Action="http://ServiceWsdl/ServiceWsdl/getWsdlResponse" message="tns:getWsdlResponse"/>
        </operation>
    </portType>
    <binding name="ServiceWsdlImplPortBinding" type="tns:ServiceWsdl">
        <soap:binding transport="http://schemas.xmlsoap.org/soap/http" style="rpc"/>
        <operation name="getWsdl">
            <soap:operation soapAction=""/>
            <input>
                <soap:body use="literal" namespace="http://ServiceWsdl/"/>
            </input>
            <output>
                <soap:body use="literal" namespace="http://ServiceWsdl/"/>
            </output>
        </operation>
    </binding>
    <service name="ServiceWsdlImplService">
        <port name="ServiceWsdlImplPort" binding="tns:ServiceWsdlImplPortBinding">
            <soap:address location="http://localhost:9000/ws/insert"/>
        </port>
    </service>
</definitions>